Remilia/__init__.py
Remilia/base/__init__.py
Remilia/base/apis.py
Remilia/base/directorys.py
Remilia/base/events.py
Remilia/base/files.py
Remilia/base/types.py
Remilia/jsondb/__init__.py
Remilia/jsondb/builder.py
Remilia/jsondb/db.py
Remilia/jsondb/dbbase.py
Remilia/lite/LiteData.py
Remilia/lite/LiteEvent.py
Remilia/lite/LiteFunctions.py
Remilia/lite/LiteI18n.py
Remilia/lite/LiteLog.py
Remilia/lite/LiteMixin.py
Remilia/lite/LitePGL.py
Remilia/lite/LiteResource.py
Remilia/lite/LiteTasks.py
Remilia/lite/LiteThread.py
Remilia/lite/__init__.py
Remilia/lite/v2/ClassMixin.py
Remilia/lite/v2/ConfigManager.py
Remilia/lite/v2/__init__.py
Remilia/lite/v2/utils.py
Remilia/utils/DecoratorUtils.py
Remilia/utils/SignParas.py
Remilia/utils/__init__.py
Remilia/utils/cli/__init__.py
Remilia/utils/cli/utils.py
Remilia/utils/cli/prompts/__init__.py
Remilia/utils/cli/prompts/checkbox.py
Remilia/utils/cli/prompts/confirm.py
Remilia/utils/cli/prompts/input.py
Remilia/utils/cli/prompts/list.py
Remilia/utils/net/__init__.py
Remilia/utils/net/pixiv.py
Remilia/utils/os/__init__.py
Remilia/utils/os/win/__init__.py
Remilia/utils/os/win/exeutils.py
Remilia/utils/thread/Timeout.py
Remilia/utils/thread/__init__.py
Remilia/utils/thread/terminable_thread.py
Remilia-2023.4.2.2.50.21.dist-info/LICENSE
Remilia-2023.4.2.2.50.21.dist-info/METADATA
Remilia-2023.4.2.2.50.21.dist-info/WHEEL
Remilia-2023.4.2.2.50.21.dist-info/top_level.txt
Remilia-2023.4.2.2.50.21.dist-info/RECORD
