Metadata-Version: 2.1
Name: Remilia
Version: 2023.4.2.2.50.21
Summary: Use python with dignity,here offer some utils
Home-page: https://github.com/IAXRetailer/Remilia
Author: h2sxxa
Author-email: H2Sxxa0w0@gmail.com
Maintainer: h2sxxa
Maintainer-email: H2Sxxa0w0@gmail.com
License: MIT License
Platform: all
Classifier: License :: OSI Approved :: MIT License
Classifier: Programming Language :: Python :: 3.6
Classifier: Programming Language :: Python :: 3.7
Classifier: Programming Language :: Python :: 3.8
Classifier: Programming Language :: Python :: 3.9
Classifier: Programming Language :: Python :: 3.10
Classifier: Programming Language :: Python :: 3.11
Requires-Dist: colorama
Requires-Dist: pyyaml
